coil/__init__.py
coil/__main__.py
coil/config.py
coil/db.py
coil/shell.py
coil/venv.py
coiled_venv-0.1.2.dist-info/LICENSE
coiled_venv-0.1.2.dist-info/METADATA
coiled_venv-0.1.2.dist-info/WHEEL
coiled_venv-0.1.2.dist-info/entry_points.txt
coiled_venv-0.1.2.dist-info/top_level.txt
coiled_venv-0.1.2.dist-info/RECORD
