Metadata-Version: 2.1
Name: coiled-venv
Version: 0.1.2
Summary: Let it hatch, watch it coil (your python virtualenv)
Author-email: Filipe Pina <fopina@skmobi.com>
License: MIT
Keywords: productivity,virtual env,cleanup,cli
Classifier: Development Status :: 4 - Beta
Classifier: Intended Audience :: Developers
Classifier: License :: OSI Approved :: MIT License
Classifier: Operating System :: OS Independent
Classifier: Programming Language :: Python
Classifier: Programming Language :: Python :: 3
Classifier: Programming Language :: Python :: 3.6
Classifier: Programming Language :: Python :: 3.7
Classifier: Programming Language :: Python :: 3.8
Classifier: Programming Language :: Python :: 3.9
Requires-Python: >=3.7
License-File: LICENSE
Provides-Extra: dev
Requires-Dist: black ==23.1.0 ; extra == 'dev'
